[
    {
        "paramId": "notesKilian",
        "link": "src/projects/notesKilian.md",
        "img": "images/kilian.webp",
        "name": "Kilian Valkhof"
    },
    {
        "paramId": "notesFenna",
        "link": "src/projects/notesFenna.md",
        "img": "images/fenna.webp",
        "name": "Fenna de Wilde"
    },
    {
        "paramId": "processWAFS",
        "link": "https://jopmolenaar.github.io/web-app-from-scratch-2324/process.md",
        "img": "images/wafsWebsites.webp",
        "name": "WAFS"
    },
    {
        "paramId": "notesJeffry",
        "link": "src/projects/notesJeffry.md",
        "img": "images/jeffryArts.webp",
        "name": "Jeffry Arts"
    },
    {
        "paramId": "notesNils",
        "link": "src/projects/notesNils.md",
        "img": "images/nilsBinder.webp",
        "name": "Nils Binder"
    },
    {
        "paramId": "notesJeremy",
        "link": "src/projects/notesJeremy.md",
        "img": "images/jeremy.webp",
        "name": "Jeremy keith"
    },
    {
        "paramId": "notesMarieke",
        "link": "src/projects/notesMarieke.md",
        "img": "images/mariekeEnPim.webp",
        "name": "Marieke en Pim"
    },
    {
        "paramId": "notesRosa",
        "link": "src/projects/notesRosa.md",
        "img": "images/rosa.webp",
        "name": "Rosa Schuurman"
    },
    {
        "paramId": "processCSS",
        "link": "https://jopmolenaar.github.io/CSS-cockpit-control/process.md",
        "img": "images/ufoCockpitCss.webp",
        "name": "CSS to the rescue"
    },
    {
        "paramId": "processBT",
        "img": "images/browserTech.webp",
        "name": "Browser tech"
    },
    {
        "paramId": "Hackathon",
        "link": "src/projects/hackathon.md",
        "img": "images/cssDayTaMockup.webp",
        "name": "Hackathon"
    },
    {
        "paramId": "processAPI",
        "link": "https://raw.githubusercontent.com/JopMolenaar/API-JopMolenaar/main/processAPI.md",
        "img": "images/pwaChat.webp",
        "name": "API"
    },
    {
        "paramId": "processHCD",
        "link": "https://raw.githubusercontent.com/JopMolenaar/HCD-videoExperienceForMarie/main/README.md",
        "img": "images/hcd.webp",
        "name": "HCD"
    },
    {
        "paramId": "Meesterproef",
        "link": "src/projects/meesterproef.md",
        "img": "images/meesterproef.webp",
        "name": "Meesterproef"
    },
    {
        "paramId": "Q42",
        "link": "src/projects/q42.md",
        "img": "images/q42.webp",
        "name": "Q42"
    },
    {
        "paramId": "LeerdoelenJop",
        "link": "src/projects/leerDoelenJop.md",
        "img": "images/leerdoelen.webp",
        "name": "Leerdoelen Jop"
    },
    {
        "paramId": "Robert",
        "link": "src/projects/notesRobert.md",
        "img": "images/robert.webp",
        "name": "Robert Spier"
    },
    {
        "paramId": "CSS-DAY",
        "link": "src/projects/cssDay.md",
        "img": "images/cssDay.webp",
        "name": "CSS DAY"
    },
    {
        "paramId": "pre-css-day",
        "link": "src/projects/preCssDay.md",
        "img": "images/preCssDay.webp",
        "name": "Pre CSS day"
    },
    {
        "paramId": "De-waag",
        "link": "src/projects/deWaag.md",
        "img": "images/deWaag.webp",
        "name": "De Waag"
    }
]